LICENSE
MANIFEST.in
README.md
VERSION
requirements.txt
setup.cfg
setup.py
bin/lisflood
src/lisf1.py
src/lisfloodSettings_reference.xml
src/lisflood/Lisflood_EnKF.py
src/lisflood/Lisflood_dynamic.py
src/lisflood/Lisflood_initial.py
src/lisflood/Lisflood_monteCarlo.py
src/lisflood/__init__.py
src/lisflood/main.py
src/lisflood/global_modules/__init__.py
src/lisflood/global_modules/add1.py
src/lisflood/global_modules/checkers.py
src/lisflood/global_modules/decorators.py
src/lisflood/global_modules/default_options.py
src/lisflood/global_modules/errors.py
src/lisflood/global_modules/netcdf.py
src/lisflood/global_modules/output.py
src/lisflood/global_modules/settings.py
src/lisflood/global_modules/stateVar.py
src/lisflood/global_modules/zusatz.py
src/lisflood/hydrological_modules/__init__.py
src/lisflood/hydrological_modules/evapowater.py
src/lisflood/hydrological_modules/frost.py
src/lisflood/hydrological_modules/groundwater.py
src/lisflood/hydrological_modules/indicatorcalc.py
src/lisflood/hydrological_modules/inflow.py
src/lisflood/hydrological_modules/kinematic_wave_parallel.py
src/lisflood/hydrological_modules/kinematic_wave_parallel_tools.py
src/lisflood/hydrological_modules/lakes.py
src/lisflood/hydrological_modules/landusechange.py
src/lisflood/hydrological_modules/leafarea.py
src/lisflood/hydrological_modules/miscInitial.py
src/lisflood/hydrological_modules/opensealed.py
src/lisflood/hydrological_modules/polder.py
src/lisflood/hydrological_modules/readmeteo.py
src/lisflood/hydrological_modules/reservoir.py
src/lisflood/hydrological_modules/riceirrigation.py
src/lisflood/hydrological_modules/routing.py
src/lisflood/hydrological_modules/snow.py
src/lisflood/hydrological_modules/soil.py
src/lisflood/hydrological_modules/soilloop.py
src/lisflood/hydrological_modules/structures.py
src/lisflood/hydrological_modules/surface_routing.py
src/lisflood/hydrological_modules/transmission.py
src/lisflood/hydrological_modules/waterabstraction.py
src/lisflood_model.egg-info/PKG-INFO
src/lisflood_model.egg-info/SOURCES.txt
src/lisflood_model.egg-info/dependency_links.txt
src/lisflood_model.egg-info/requires.txt
src/lisflood_model.egg-info/top_level.txt
src/lisflood_model.egg-info/zip-safe