Metadata-Version: 2.1
Name: lisflood-model
Version: 4.3.1
Summary: LISFLOOD model python module
Home-page: https://github.com/ec-jrc/lisflood-code
Download-URL: https://github.com/ec-jrc/lisflood-code/archive/4.3.1.tar.gz
Author: Ad de Roo, Emiliano Gelati, Peter Burek, Johan van der Knijff, Niko Wanders
Author-email: carlo.russo@ext.ec.europa.eu
License: EUPL 1.2
Keywords: lisflood,lisvap,efas,glofas,copernicus,ecmwf
Classifier: Development Status :: 5 - Production/Stable
Classifier: Intended Audience :: Developers
Classifier: Intended Audience :: Education
Classifier: Intended Audience :: Financial and Insurance Industry
Classifier: Intended Audience :: Other Audience
Classifier: Intended Audience :: Science/Research
Classifier: License :: OSI Approved :: European Union Public Licence 1.2 (EUPL 1.2)
Classifier: Operating System :: Unix
Classifier: Operating System :: POSIX
Classifier: Operating System :: Microsoft :: Windows
Classifier: Operating System :: MacOS :: MacOS X
Classifier: Programming Language :: Python
Classifier: Programming Language :: Python :: 3.7
Classifier: Topic :: Scientific/Engineering :: Physics
License-File: LICENSE
